soda_python_sdk/__init__.py
soda_python_sdk/crypto.py
soda_python_sdk/test.py
soda_bubble_sdk-0.0.11.dist-info/METADATA
soda_bubble_sdk-0.0.11.dist-info/WHEEL
soda_bubble_sdk-0.0.11.dist-info/top_level.txt
soda_bubble_sdk-0.0.11.dist-info/RECORD
